{"cameraMode":{"drawMode":0,"name":"Shaded","section":"Shading Mode"},"sceneLighting":false,"audioPlay":false,"sceneViewState":{"showFog":true,"showMaterialUpdate":false,"showSkybox":false,"showFlares":true,"showImageEffects":true,"showParticleSystems":true},"in2DMode":false,"pivot":{"x":-0.17061300575733186,"y":0.05251626670360565,"z":-0.2518894672393799},"rotation":{"x":-0.11635144799947739,"y":0.10763923823833466,"z":-0.012685246765613556,"w":-0.9872778654098511},"size":0.8083316683769226,"orthographic":false}